sandwichR/__init__.py
sandwichR/sandwich_avoid.py
sandwichR/sandwich_baseboard.py
sandwichR/sandwich_camera.py
sandwichR/sandwich_config.py
sandwichR/sandwich_linetrace.py
sandwichR/pins/pins.config
sandwichR-0.0.14.dist-info/METADATA
sandwichR-0.0.14.dist-info/WHEEL
sandwichR-0.0.14.dist-info/top_level.txt
sandwichR-0.0.14.dist-info/RECORD
