Metadata-Version: 2.1
Name: sandwichR
Version: 0.0.14
Summary: Python library for Sandwich
Home-page: https://eng.roborobo.co.kr/main
Author: Roborobo
Author-email: roborobolab@gmail.com
License: UNKNOWN
Download-URL: https://github.com/RoboroboLab/Sandwich/archive/master.tar.gz
Keywords: sandwichR,roborobo
Platform: UNKNOWN
Classifier: Programming Language :: Python :: 3
Classifier: Programming Language :: Python :: 3.2
Classifier: Programming Language :: Python :: 3.3
Classifier: Programming Language :: Python :: 3.4
Classifier: Programming Language :: Python :: 3.5
Classifier: Programming Language :: Python :: 3.6
Requires-Python: >=3
